{
  "name": "Leon Morales",
  "age": 65,
  "address": {
    "street": "Furaz Boulevard",
    "city": "Sopeuni",
    "state": "MD",
    "zip": "13009"
  },
  "contact": {
    "phone": "(851) 465-3647",
    "servicePhone": "800741119"
  },
  "birthday": "1975-08-26T20:11:25.735Z",
  "ip": "4.86.8.67",
  "foo": "bar",
  "profile": {
    "about": "Nuv tez lojufege pilodi damwara ta fuzzib wu sum wukza otvan cosuil lirmimuj tijrufpa laibi gi. Ileneatu agozle fegis fodeze mib zojeek kolow pip imeje evurobde ape ipibez bav de ir. Fadhovoc of tuhod omokemhib cadcajare zimnor pepracge fidvi ozvorwu devi revkic cupbod fud bucecha zak piz car negajkuj. Ma rivacubo oka geul cil ussub wirzecla bo vezomgin wiwiso cepartiw becikipuv uti dosife.",
    "bio": "Hud uridevsi tokcac levabpeh hugjihov lujipopim ocoaso no vum zaodusok ohajitu capiri fe zeloko bozotpo. Miz igbejam jazwuwuv juf jowon juwiwor wedpak pipzid miuzbi ihebe bokemi debi. Asaguwi du ewiha gir ravosaoj ehhusud nu ceda guhpawjo holeimo iwuegu ro irooziv ma zemzus faoz wemaczew."
  },
  "apiKey": "1b12fe466ca11649f2369beebc575b73819f94f8b672bfe05bf45c8df067b071",
  "currency": {
    "code": "AUD",
    "name": "Australia Dollar"
  }
}