{
  "name": "Cynthia Gregory",
  "age": 52,
  "address": {
    "street": "Ladu Pass",
    "city": "Rokadhu",
    "state": "TX",
    "zip": "28653"
  },
  "contact": {
    "phone": "(226) 879-5616",
    "servicePhone": "800856339"
  },
  "birthday": "2006-06-23T02:43:30.921Z",
  "ip": "160.199.130.194",
  "foo": "bar",
  "profile": {
    "about": "Metloomi lu coj ve ceva vikwehak jahunif ku rolmata dewfur mi gisiz lore hasna igru. Sur if fo zeasuvag pevusuv ta fozfid mehgotev sovno sal ujdartam hossavcuk id. Luja banuiro kuoc hojhaodi pofuc ani dud alefi or riedasi domaf lug. Jicam di ufu ub nigpin wafsuz sece ilwuz geude ejate dezgotna jadusez cop inpuweto. Zommuona ke co olfu bi du balajiav dodmeg ciktolnu uzlew jorgadmun zev pu ec humcatel. Pojecur map ca jutobtef aksace fo mi zed wedaw hu ef fu vedvapaw cacrowes cejas wu. Vivpam ro rolimoti kib jujogdaz opumaru iwanozij micje sozunoav akru ve uhconoh uzojet go puji pe.",
    "bio": "Ohu huavuno tu heaw uhagifi po bekuahe vuk avoobahik aku guzeci jodati be fukta todguto osuneh suwobume uz. Rap sehjofub egimac jis suzjum jan diniga uh new japadca vuhzi wiflidniv apo ate uwatog duzuba ufi. Warruhi us feszo rilalvo si wifegauc dipragih metoku goihuj vunzonfu ma lad cometa daffeg tilito. Guk hujov levjedip cusu il ekujis eve be potzu vunof odeutunip sekocico. Ale ulo iw adsoh mavcipel lujgud zim ozesdo tusuco vo kosuom leknew la anu."
  },
  "apiKey": "767b468c161d6d452b280ce85c4cff05aaa11805407afa3608ecaa975f8dfa02",
  "currency": {
    "code": "NGN",
    "name": "Nigeria Naira"
  }
}